lantern3/__init__.py
lantern3/main.py
lantern3/builder/__init__.py
lantern3/builder/flashbots.py
lantern3-0.1.0.dist-info/LICENSE
lantern3-0.1.0.dist-info/METADATA
lantern3-0.1.0.dist-info/WHEEL
lantern3-0.1.0.dist-info/top_level.txt
lantern3-0.1.0.dist-info/RECORD
