Metadata-Version: 2.1
Name: lantern3
Version: 0.1.0
Summary: Light up the Ethereum blockchain
Home-page: https://github.com/taekop/lantern3.py
Author: taekop
Author-email: taekop@naver.com
License: MIT
Keywords: ethereum
Classifier: Programming Language :: Python :: 3
Classifier: License :: OSI Approved :: MIT License
Classifier: Operating System :: OS Independent
Requires-Python: >=3.9,<4.0
License-File: LICENSE
Requires-Dist: web3 (<7,>=6.0.0)
